drudge_cli-2.2.5.dist-info/licenses/LICENSE
worklog/__init__.py
worklog/__main__.py
worklog/config.py
worklog/config.yaml.example
worklog/models.py
worklog/validators.py
worklog/cli/__init__.py
worklog/cli/commands.py
worklog/managers/__init__.py
worklog/managers/backup.py
worklog/managers/daily_file.py
worklog/managers/worklog.py
worklog/sync/__init__.py
worklog/sync/sheets.py
worklog/utils/__init__.py
worklog/utils/decorators.py
drudge_cli-2.2.5.dist-info/METADATA
drudge_cli-2.2.5.dist-info/WHEEL
drudge_cli-2.2.5.dist-info/entry_points.txt
drudge_cli-2.2.5.dist-info/top_level.txt
drudge_cli-2.2.5.dist-info/RECORD
