Metadata-Version: 2.4
Name: drudge-cli
Version: 2.2.5
Summary: 🚀 A powerful work time tracking tool for the command line
Author-email: Trik16 <trik.sedici@gmail.com>
License-Expression: MIT
Project-URL: Homepage, https://github.com/Trik16/drudge
Project-URL: Documentation, https://github.com/Trik16/drudge#readme
Project-URL: Repository, https://github.com/Trik16/drudge.git
Project-URL: Issues, https://github.com/Trik16/drudge/issues
Project-URL: Changelog, https://github.com/Trik16/drudge/releases
Keywords: time-tracking,productivity,cli,worklog,time-management,task-tracking,command-line,typer
Classifier: Development Status :: 4 - Beta
Classifier: Intended Audience :: Developers
Classifier: Intended Audience :: End Users/Desktop
Classifier: Operating System :: OS Independent
Classifier: Programming Language :: Python :: 3
Classifier: Programming Language :: Python :: 3.8
Classifier: Programming Language :: Python :: 3.9
Classifier: Programming Language :: Python :: 3.10
Classifier: Programming Language :: Python :: 3.11
Classifier: Programming Language :: Python :: 3.12
Classifier: Programming Language :: Python :: 3.13
Classifier: Topic :: Office/Business
Classifier: Topic :: Utilities
Classifier: Environment :: Console
Classifier: Typing :: Typed
Requires-Python: >=3.8
License-File: LICENSE
Requires-Dist: typer[all]>=0.9.0
Requires-Dist: rich>=13.0.0
Requires-Dist: pyyaml>=6.0.0
Requires-Dist: gspread>=5.12.0
Requires-Dist: google-auth>=2.23.0
Requires-Dist: google-api-python-client>=2.108.0
Provides-Extra: sheets
Requires-Dist: haunts>=0.7.0; extra == "sheets"
Provides-Extra: dev
Requires-Dist: pytest>=7.0.0; extra == "dev"
Requires-Dist: black>=23.0.0; extra == "dev"
Requires-Dist: mypy>=1.0.0; extra == "dev"
Requires-Dist: ruff>=0.1.0; extra == "dev"
Provides-Extra: test
Requires-Dist: pytest>=7.0.0; extra == "test"
Requires-Dist: pytest-cov>=4.0.0; extra == "test"
Dynamic: license-file
